gsl_protocol/__init__.py
gsl_protocol/hedgehog_protocol
gsl_protocol/proto_target.py
gsl_protocol/grammar/HedgehogProtocol.g4
gsl_protocol/grammar/HedgehogProtocol.tokens
gsl_protocol/grammar/HedgehogProtocolLexer.py
gsl_protocol/grammar/HedgehogProtocolLexer.tokens
gsl_protocol/grammar/HedgehogProtocolParser.py
gsl_protocol/grammar/HedgehogProtocolVisitor.g4v
gsl_protocol/grammar/HedgehogProtocolVisitor.py
gsl_protocol/grammar/__init__.py
hedgehog_protocol_spec-0.9.0.dist-info/LICENSE
hedgehog_protocol_spec-0.9.0.dist-info/METADATA
hedgehog_protocol_spec-0.9.0.dist-info/WHEEL
hedgehog_protocol_spec-0.9.0.dist-info/entry_points.txt
hedgehog_protocol_spec-0.9.0.dist-info/top_level.txt
hedgehog_protocol_spec-0.9.0.dist-info/RECORD
